[{"x":191,"y":38,"type":"start","id":"b2a880ff-a339-ee30-aa59-603bbcd55257","next":[{"x":231,"y":178,"type":"diamond"}],"previous":{"x":0,"y":0},"userdata":["v1","v2"]},{"x":249,"y":532,"type":"end","id":"6bc0685f-5fca-7a0f-d85c-53deffb3fd25","next":[{"x":0,"y":0}],"previous":{"x":128,"y":409,"type":"addition"},"userdata":[]},{"x":231,"y":178,"type":"diamond","id":"c4dfd78f-0629-78a8-85b0-2ba037d89503","next":[{"x":128,"y":409,"type":"addition"},{"x":459,"y":377,"type":"subtraction"}],"previous":{"x":191,"y":38,"type":"start"},"userdata":["v1","v2","action","addition","subtraction"]},{"x":459,"y":377,"type":"subtraction","id":"63ce3fe3-bc86-1ff4-d418-84468763deed","next":[{"x":249,"y":532,"type":"end"}],"previous":{"x":231,"y":178,"type":"diamond"},"userdata":[]},{"x":128,"y":409,"type":"addition","id":"602a5e86-d871-3d8e-eb07-e70e25dd13ed","next":[{"x":249,"y":532,"type":"end"}],"previous":{"x":231,"y":178,"type":"diamond"},"userdata":[]}]